step_cli_tools/__init__.py
step_cli_tools/common.py
step_cli_tools/configuration.py
step_cli_tools/main.py
step_cli_tools/models/data.py
step_cli_tools/models/select.py
step_cli_tools/operations.py
step_cli_tools/utils/ca.py
step_cli_tools/utils/certificates.py
step_cli_tools/utils/general.py
step_cli_tools/utils/network.py
step_cli_tools/utils/paths.py
step_cli_tools/utils/validators.py
step_cli_tools-0.3.0.dist-info/METADATA
step_cli_tools-0.3.0.dist-info/WHEEL
step_cli_tools-0.3.0.dist-info/entry_points.txt
step_cli_tools-0.3.0.dist-info/licenses/LICENSE
step_cli_tools-0.3.0.dist-info/RECORD
