Metadata-Version: 2.4
Name: step-cli-tools
Version: 0.3.0
Summary: Prebuilt tools for the smallstep step-cli
License-Expression: MIT
License-File: LICENSE
Keywords: step-ca,step-cli,ca,cli,certificate,certificate-authority
Author: LeoTN
Author-email: LeoTN.GitHub@gmx.net
Requires-Python: >=3.10,<4.0
Classifier: Topic :: Utilities
Classifier: Environment :: Console
Classifier: Programming Language :: Python :: 3
Classifier: Operating System :: OS Independent
Requires-Dist: cryptography (>=46.0.3,<47.0.0)
Requires-Dist: packaging (>=25.0,<26.0)
Requires-Dist: questionary (==2.1.1)
Requires-Dist: requests (>=2.32.5,<3.0.0)
Requires-Dist: rich (>=14.2.0,<15.0.0)
Requires-Dist: ruamel-yaml (>=0.19.1,<0.20.0)
Project-URL: Bug Tracker, https://github.com/LeoTN/step-cli-tools/issues
Project-URL: Homepage, https://github.com/LeoTN/step-cli-tools#readme
Project-URL: Repository, https://github.com/LeoTN/step-cli-tools
